sweetconfusionmatrix/__init__.py
sweetconfusionmatrix/sweetconfusionmatrix.py
sweetconfusionmatrix-0.2.dist-info/LICENSE
sweetconfusionmatrix-0.2.dist-info/METADATA
sweetconfusionmatrix-0.2.dist-info/WHEEL
sweetconfusionmatrix-0.2.dist-info/top_level.txt
sweetconfusionmatrix-0.2.dist-info/RECORD
