Metadata-Version: 2.1
Name: sweetconfusionmatrix
Version: 0.2
Summary: A tool to generate sweet confusion matrix
Home-page: https://github.com/cedced19/sweet-confusion-matrix
Author: Cédric Jung
Author-email: cedced19@gmail.com
License: UNKNOWN
Platform: UNKNOWN
Classifier: Programming Language :: Python :: 3
Classifier: License :: OSI Approved :: MIT License
Classifier: Operating System :: OS Independent
License-File: LICENSE
Requires-Dist: matplotlib
Requires-Dist: seaborn
Requires-Dist: sklearn
Requires-Dist: pandas
Requires-Dist: numpy
